Pre_processamento/__init__.py
Pre_processamento/Pre_eng/P_eng.py
Pre_processamento/Pre_eng/Pro_eng.py
Pre_processamento/Pre_eng/__init__.py
Pre_processamento/Pre_pt_br/P_pt_br.py
Pre_processamento/Pre_pt_br/Pro_pt_br.py
Pre_processamento/Pre_pt_br/__init__.py
Pre_processamento-0.0.1.dist-info/METADATA
Pre_processamento-0.0.1.dist-info/WHEEL
Pre_processamento-0.0.1.dist-info/top_level.txt
Pre_processamento-0.0.1.dist-info/RECORD
