Metadata-Version: 2.1
Name: Pre-processamento
Version: 0.0.1
Summary: Pré-processamento de corpus para português e inglês usando spaCy.
Home-page: https://github.com/alexxs2/Pr--processamento.pacote
Author: Alexsandro Da Silva Bezerra
Author-email: alecsbezerra@gmail.com
Requires-Python: >=3.8
Requires-Dist: spacy
